formresponses/__init__.py
formresponses/formresponses.py
formresponses/main.py
googleforms/__init__.py
googleforms/main.py
formresponses-0.1.2.dist-info/LICENSE.txt
formresponses-0.1.2.dist-info/METADATA
formresponses-0.1.2.dist-info/WHEEL
formresponses-0.1.2.dist-info/top_level.txt
formresponses-0.1.2.dist-info/RECORD
