Metadata-Version: 2.1
Name: formresponses
Version: 0.1.2
Summary: Send Google Forms responses using Python
Author: J3pe
Keywords: python,requests,google,forms,form
Classifier: Intended Audience :: Developers
Classifier: Programming Language :: Python :: 3
Classifier: Operating System :: Unix
Classifier: Operating System :: MacOS :: MacOS X
Classifier: Operating System :: Microsoft :: Windows
License-File: LICENSE.txt
Requires-Dist: requests
